bonus_click/__init__.py
bonus_click/_options/__init__.py
bonus_click/_options/enum_option.py
bonus_click/options.py
bonus_click/py.typed
bonus_click-0.3.0.dist-info/METADATA
bonus_click-0.3.0.dist-info/WHEEL
bonus_click-0.3.0.dist-info/licenses/AUTHORS.md
bonus_click-0.3.0.dist-info/licenses/LICENSE.md
bonus_click-0.3.0.dist-info/RECORD
