Metadata-Version: 2.4
Name: bonus_click
Version: 0.3.0
Summary: Convenience wrappers around helpful click patterns.
License-File: AUTHORS.md
License-File: LICENSE.md
Author: Devon Bray
Requires-Python: >=3.10,<4.0
Classifier: Programming Language :: Python :: 3
Classifier: Programming Language :: Python :: 3.10
Classifier: Programming Language :: Python :: 3.11
Classifier: Programming Language :: Python :: 3.12
Classifier: Programming Language :: Python :: 3.13
Classifier: Programming Language :: Python :: 3.14
Requires-Dist: click (>=8.3.0,<9.0.0)
Project-URL: Homepage, https://github.com/esologic/bonus-click
Project-URL: Source, https://github.com/esologic/bonus-click
Project-URL: Tracker, https://github.com/esologic/bonus-click/issues
